explay/__init__.py
explay/agg_func.py
explay/merger.py
explay/openpyxl_ext.py
explay/parser.py
explay/post_func.py
explay/source.py
explay/utils.py
explay_testr-0.4.0.data/scripts/exp
explay_testr-0.4.0.dist-info/DESCRIPTION.rst
explay_testr-0.4.0.dist-info/METADATA
explay_testr-0.4.0.dist-info/RECORD
explay_testr-0.4.0.dist-info/WHEEL
explay_testr-0.4.0.dist-info/metadata.json
explay_testr-0.4.0.dist-info/top_level.txt
